kartingpros/T1_AI.py
kartingpros/T2_AI.py
kartingpros/__main__.py
kartingpros/car.py
kartingpros/draw_track.py
kartingpros/loadimage.py
kartingpros/main.py
kartingpros/mainmenu.py
kartingpros/race_computer.py
kartingpros/screen.py
kartingpros/settings.json
kartingpros/settings.py
kartingpros/timetrial.py
kartingpros/timetrial2.py
kartingpros/track.py
kartingpros/track2.py
kartingpros/two_player.py
kartingpros/two_player2.py
kartingpros/ArtificalIntelligence/AI_Testing.ipynb
kartingpros/ArtificalIntelligence/features.npy
kartingpros/ArtificalIntelligence/knn_model.pkl
kartingpros/ArtificalIntelligence/track1_easy.npy
kartingpros/ArtificalIntelligence/track1_hard.npy
kartingpros/ArtificalIntelligence/track2_easy.npy
kartingpros/ArtificalIntelligence/track2_hard.npy
kartingpros/fonts/American Captain.ttf
kartingpros/images/Gui_background.png
kartingpros/images/ai_trophy.png
kartingpros/images/bricks.png
kartingpros/images/car.png
kartingpros/images/crash.png
kartingpros/images/f1sprite.png
kartingpros/images/f1sprite2.png
kartingpros/images/grass.png
kartingpros/images/lightsout.gif
kartingpros/images/p1_trophy.png
kartingpros/images/p2_trophy.png
kartingpros/images/track.png
kartingpros/images/track1-min.png
kartingpros/images/track1-minb.png
kartingpros/images/track1.png
kartingpros/images/track1_drawn.png
kartingpros/images/track2.png
kartingpros/images/track21.png
kartingpros/images/track2b.png
kartingpros/images/track_black.png
kartingpros/images/trophy.png
kartingpros/images/tutorial.png
kartingpros/images/win.png
kartingpros/images/starting_lights/lights1.png
kartingpros/images/starting_lights/lights2.png
kartingpros/images/starting_lights/lights3.png
kartingpros/images/starting_lights/lights4.png
kartingpros/sounds/car_crash.mp3
kartingpros/sounds/crowd.mp3
kartingpros/sounds/crowd.wav
kartingpros/sounds/menu.mp3
kartingpros/sounds/race_coundown.mp3
kartingpros/sounds/rev.mp3
kartingpros/sounds/rev.wav
kartingpros/sounds/win.wav
kartingpros-1.0.0.dist-info/LICENSE.txt
kartingpros-1.0.0.dist-info/METADATA
kartingpros-1.0.0.dist-info/WHEEL
kartingpros-1.0.0.dist-info/entry_points.txt
kartingpros-1.0.0.dist-info/top_level.txt
kartingpros-1.0.0.dist-info/RECORD
