Metadata-Version: 2.1
Name: kartingpros
Version: 1.0.0
Summary: A 2D racing game
Home-page: https://github.com/kosta2456/Karting-Pros
Author: Vishvak Seenichamy, Kevin Kosta, Wesley Boyd, Carson Hamel
Author-email: vishvak@vishvak.com
License: UNKNOWN
Platform: UNKNOWN
Requires-Dist: pygame (==1.9.6)
Requires-Dist: numpy (==1.18.4)
